{"assets/images/client-1.png":["assets/images/client-1.png"],"assets/images/client-2.png":["assets/images/client-2.png"],"assets/images/client-3.jpg":["assets/images/client-3.jpg"],"assets/images/client-4.png":["assets/images/client-4.png"],"assets/images/client-5.jpg":["assets/images/client-5.jpg"],"assets/images/list.jpeg":["assets/images/list.jpeg"],"assets/images/logo.png":["assets/images/logo.png"],"assets/images/logotip.png":["assets/images/logotip.png"],"assets/images/photo.png":["assets/images/photo.png"],"assets/images/vchd_logo.jpg":["assets/images/vchd_logo.jpg"],"packages/cupertino_icons/assets/CupertinoIcons.ttf":["packages/cupertino_icons/assets/CupertinoIcons.ttf"]}